{"_last_updated":"Sat, 13 Oct 2018 21:53:24 +0000","ID":"CF5bc26604eaf3c","cf_version":"1.7.3-a.1","name":"Calculations Checkbox","scroll_top":0,"success":"Form has been successfully submitted. Thank you.\t\t\t\t\t\t\t\t\t","db_support":1,"pinned":0,"hide_form":1,"avatar_field":"","form_ajax":1,"custom_callback":"","layout_grid":{"fields":{"fld_2069847":"1:1","fld_3100099":"2:1","fld_5764774":"2:1","fld_2526988":"2:1","fld_3364767":"2:2","fld_6418208":"2:2","fld_522650":"2:2","fld_1629134":"2:2"},"structure":"12|6:6"},"fields":{"fld_2069847":{"ID":"fld_2069847","type":"html","label":"html__fld_2069847","slug":"html__fld_2069847","conditions":{"type":""},"caption":"","config":{"custom_class":"","default":"Calculations Checkbox  - CF5bc26604eaf3c"}},"fld_3100099":{"ID":"fld_3100099","type":"checkbox","label":"Checkbox 1","slug":"checkbox_1","conditions":{"type":"con_8512128212820608"},"caption":"","config":{"custom_class":"","default_option":"","auto_type":"","taxonomy":"category","post_type":"post","value_field":"name","orderby_tax":"name","orderby_post":"name","order":"ASC","default":"","option":{"opt1077006":{"calc_value":1,"value":1,"label":1},"opt1564738":{"calc_value":2,"value":2,"label":2},"opt1328155":{"calc_value":3,"value":3,"label":3}},"email_identifier":0,"personally_identifying":0}},"fld_5764774":{"ID":"fld_5764774","type":"checkbox","label":"Checkbox 2","slug":"checkbox_2","conditions":{"type":""},"caption":"","config":{"custom_class":"","default_option":"","auto_type":"","taxonomy":"category","post_type":"post","value_field":"name","orderby_tax":"name","orderby_post":"name","order":"ASC","default":"","show_values":1,"option":{"opt1140160":{"calc_value":10.001,"value":10001,"label":10.001},"opt1361898":{"calc_value":10.002,"value":10002,"label":10.002},"opt1427240":{"calc_value":10.003,"value":10003,"label":10.003}},"email_identifier":0,"personally_identifying":0}},"fld_3364767":{"ID":"fld_3364767","type":"calculation","label":"Auto Calc With Rounding","slug":"auto_calc_with_rounding","conditions":{"type":""},"caption":"","config":{"custom_class":"","element":"h3","classes":"total-line","before":"Total:","after":"","fixed":1,"thousand_separator":",","decimal_separator":".","formular":" ( fld_3100099+fld_5764774 ) ","config":{"group":[{"lines":[{"operator":"+","field":"fld_3100099"},{"operator":"+","field":"fld_5764774"}]}]},"manual_formula":"","email_identifier":0,"personally_identifying":0}},"fld_6418208":{"ID":"fld_6418208","type":"calculation","label":"Auto Calc Without Rounding","slug":"auto_calc_without_rounding","conditions":{"type":""},"caption":"","config":{"custom_class":"","element":"h3","classes":"total-line","before":"Total:","after":"","thousand_separator":",","decimal_separator":".","formular":" ( fld_3100099+fld_5764774 ) ","config":{"group":[{"lines":[{"operator":"+","field":"fld_3100099"},{"operator":"+","field":"fld_5764774"}]}]},"manual_formula":"","email_identifier":0,"personally_identifying":0}},"fld_522650":{"ID":"fld_522650","type":"calculation","label":"Manual Calc With Rounding","slug":"manual_calc_with_rounding","conditions":{"type":""},"caption":"","config":{"custom_class":"","element":"h3","classes":"total-line","before":"Total:","after":"","fixed":1,"thousand_separator":",","decimal_separator":".","manual":1,"formular":"","config":"","manual_formula":"%checkbox_2% + %checkbox_1%","email_identifier":0,"personally_identifying":0}},"fld_1629134":{"ID":"fld_1629134","type":"calculation","label":"Manual Calc Without Rounding","slug":"manual_calc_without_rounding","conditions":{"type":""},"caption":"","config":{"custom_class":"","element":"h3","classes":"total-line","before":"Total:","after":"","thousand_separator":",","decimal_separator":".","manual":1,"formular":"","config":"","manual_formula":"%checkbox_2% + %checkbox_1%","email_identifier":0,"personally_identifying":0}},"fld_2526988":{"ID":"fld_2526988","type":"dropdown","label":"Hide Check 1","slug":"hide_check_1","conditions":{"type":""},"caption":"","config":{"custom_class":"","placeholder":"","default_option":"","auto_type":"","taxonomy":"category","post_type":"post","value_field":"name","orderby_tax":"count","orderby_post":"ID","order":"ASC","default":"","option":{"opt1996944":{"calc_value":"","value":"Yes","label":"Yes"}},"email_identifier":0,"personally_identifying":0}}},"page_names":["Page 1"],"mailer":{"on_insert":1,"sender_name":"Caldera Forms Notification","sender_email":"test@test.com","reply_to":"","email_type":"html","recipients":"","bcc_to":"","email_subject":"Calculations Checkbox","email_message":"{summary}"},"check_honey":1,"antispam":{"sender_name":"","sender_email":""},"conditional_groups":{"conditions":{"con_8512128212820608":{"id":"con_8512128212820608","name":"Hide Check 1","type":"hide","group":{"rw581696453396471":{"cl4357604965646677":{"parent":"rw581696453396471","field":"fld_2526988","compare":"is","value":"opt1996944"}}},"fields":{"cl4357604965646677":"fld_2526988"}}}},"settings":{"responsive":{"break_point":"sm"}},"privacy_exporter_enabled":false,"version":"1.7.3-a.1","db_id":"178","type":"primary"}